pikadantic/__init__.py
pikadantic/__version__.py
pikadantic/decorators.py
pikadantic/exceptions.py
pikadantic-0.0.2.dist-info/METADATA
pikadantic-0.0.2.dist-info/WHEEL
pikadantic-0.0.2.dist-info/licenses/LICENSE
pikadantic-0.0.2.dist-info/RECORD
