Metadata-Version: 2.4
Name: pikadantic
Version: 0.0.2
Summary: Pikadantic provides robust data validation for RabbitMQ messaging
Project-URL: Repository, https://github.com/karta9821/pikadantic
Project-URL: Homepage, https://github.com/karta9821/pikadantic
License: The MIT License (MIT)
License-File: LICENSE
Classifier: Framework :: Hatch
Classifier: License :: OSI Approved :: MIT License
Classifier: Programming Language :: Python
Classifier: Programming Language :: Python :: 3.9
Classifier: Programming Language :: Python :: 3.10
Classifier: Programming Language :: Python :: 3.11
Classifier: Programming Language :: Python :: 3.12
Classifier: Programming Language :: Python :: 3.13
Requires-Python: >=3.9
Requires-Dist: pika>=1.3.2
Requires-Dist: pydantic>=2.11.4
